registry_api_v2_client/__init__.py
registry_api_v2_client/exceptions.py
registry_api_v2_client/models.py
registry_api_v2_client/push.py
registry_api_v2_client/registry.py
registry_api_v2_client/core/__init__.py
registry_api_v2_client/core/connectivity.py
registry_api_v2_client/core/session.py
registry_api_v2_client/core/types.py
registry_api_v2_client/operations/__init__.py
registry_api_v2_client/operations/blobs.py
registry_api_v2_client/operations/images.py
registry_api_v2_client/operations/manifests.py
registry_api_v2_client/operations/repositories.py
registry_api_v2_client/tar/__init__.py
registry_api_v2_client/tar/processor.py
registry_api_v2_client/tar/tags.py
registry_api_v2_client/tar/validator.py
registry_api_v2_client/utils/__init__.py
registry_api_v2_client/utils/inspect.py
registry_api_v2_client/utils/validator.py
registry_api_v2_client-1.2.0.dist-info/METADATA
registry_api_v2_client-1.2.0.dist-info/WHEEL
registry_api_v2_client-1.2.0.dist-info/licenses/LICENSE
registry_api_v2_client-1.2.0.dist-info/RECORD
